utils/__init__.py
utils/log.py
utils/mqtt.py
feu_utils-0.1.3.dist-info/LICENSE
feu_utils-0.1.3.dist-info/WHEEL
feu_utils-0.1.3.dist-info/METADATA
feu_utils-0.1.3.dist-info/RECORD
